{"Identifier":"scarlet-violet-shiny","Name":"Scarlet-Violet Shiny","SlotCount":521,"Boxes":[{"BoxNumber":1,"Slots":[{"Identifier":"0004","Name":"Charmander","IsShiny":true,"IsAvailable":true,"IsEmpty":false,"Serebii":"charmander"},{"Identifier":"0005","Name":"Charmeleon","IsShiny":true,"IsAvailable":true,"IsEmpty":false,"Serebii":"charmeleon"},{"Identifier":"0006","Name":"Charizard","IsShiny":true,"IsAvailable":true,"IsEmpty":false,"Serebii":"charizard"},{"Identifier":"0025","Name":"Pikachu","IsShiny":true,"IsAvailable":true,"IsEmpty":false,"Serebii":"pikachu"},{"Identifier":"0025-f","Name":"Pikachu (Female)","IsShiny":true,"IsAvailable":true,"IsEmpty":false,"Serebii":"pikachu"},{"Identifier":"0026","Name":"Raichu","IsShiny":true,"IsAvailable":true,"IsEmpty":false,"Serebii":"raichu"},{"Identifier":"0026-f","Name":"Raichu (Female)","IsShiny":true,"IsAvailable":true,"IsEmpty":false,"Serebii":"raichu"},{"Identifier":"0039","Name":"Jigglypuff","IsShiny":true,"IsAvailable":true,"IsEmpty":false,"Serebii":"jigglypuff"},{"Identifier":"0040","Name":"Wigglytuff","IsShiny":true,"IsAvailable":true,"IsEmpty":false,"Serebii":"wigglytuff"},{"Identifier":"0048","Name":"Venonat","IsShiny":true,"IsAvailable":true,"IsEmpty":false,"Serebii":"venonat"},{"Identifier":"0049","Name":"Venomoth","IsShiny":true,"IsAvailable":true,"IsEmpty":false,"Serebii":"venomoth"},{"Identifier":"0050","Name":"Diglett","IsShiny":true,"IsAvailable":true,"IsEmpty":false,"Serebii":"diglett"},{"Identifier":"0051","Name":"Dugtrio","IsShiny":true,"IsAvailable":true,"IsEmpty":false,"Serebii":"dugtrio"},{"Identifier":"0052","Name":"Meowth","IsShiny":true,"IsAvailable":true,"IsEmpty":false,"Serebii":"meowth"},{"Identifier":"0053","Name":"Persian","IsShiny":true,"IsAvailable":true,"IsEmpty":false,"Serebii":"persian"},{"Identifier":"0054","Name":"Psyduck","IsShiny":true,"IsAvailable":true,"IsEmpty":false,"Serebii":"psyduck"},{"Identifier":"0055","Name":"Golduck","IsShiny":true,"IsAvailable":true,"IsEmpty":false,"Serebii":"golduck"},{"Identifier":"0056","Name":"Mankey","IsShiny":true,"IsAvailable":true,"IsEmpty":false,"Serebii":"mankey"},{"Identifier":"0057","Name":"Primeape","IsShiny":true,"IsAvailable":true,"IsEmpty":false,"Serebii":"primeape"},{"Identifier":"0058","Name":"Growlithe","IsShiny":true,"IsAvailable":true,"IsEmpty":false,"Serebii":"growlithe"},{"Identifier":"0059","Name":"Arcanine","IsShiny":true,"IsAvailable":true,"IsEmpty":false,"Serebii":"arcanine"},{"Identifier":"0079","Name":"Slowpoke","IsShiny":true,"IsAvailable":true,"IsEmpty":false,"Serebii":"slowpoke"},{"Identifier":"0080","Name":"Slowbro","IsShiny":true,"IsAvailable":true,"IsEmpty":false,"Serebii":"slowbro"},{"Identifier":"0081","Name":"Magnemite","IsShiny":true,"IsAvailable":true,"IsEmpty":false,"Serebii":"magnemite"},{"Identifier":"0082","Name":"Magneton","IsShiny":true,"IsAvailable":true,"IsEmpty":false,"Serebii":"magneton"},{"Identifier":"0088","Name":"Grimer","IsShiny":true,"IsAvailable":true,"IsEmpty":false,"Serebii":"grimer"},{"Identifier":"0089","Name":"Muk","IsShiny":true,"IsAvailable":true,"IsEmpty":false,"Serebii":"muk"},{"Identifier":"0090","Name":"Shellder","IsShiny":true,"IsAvailable":true,"IsEmpty":false,"Serebii":"shellder"},{"Identifier":"0091","Name":"Cloyster","IsShiny":true,"IsAvailable":true,"IsEmpty":false,"Serebii":"cloyster"},{"Identifier":"0092","Name":"Gastly","IsShiny":true,"IsAvailable":true,"IsEmpty":false,"Serebii":"gastly"}]},{"BoxNumber":2,"Slots":[{"Identifier":"0093","Name":"Haunter","IsShiny":true,"IsAvailable":true,"IsEmpty":false,"Serebii":"haunter"},{"Identifier":"0094","Name":"Gengar","IsShiny":true,"IsAvailable":true,"IsEmpty":false,"Serebii":"gengar"},{"Identifier":"0096","Name":"Drowzee","IsShiny":true,"IsAvailable":true,"IsEmpty":false,"Serebii":"drowzee"},{"Identifier":"0097","Name":"Hypno","IsShiny":true,"IsAvailable":true,"IsEmpty":false,"Serebii":"hypno"},{"Identifier":"0097-f","Name":"Hypno (Female)","IsShiny":true,"IsAvailable":true,"IsEmpty":false,"Serebii":"hypno"},{"Identifier":"0100","Name":"Voltorb","IsShiny":true,"IsAvailable":true,"IsEmpty":false,"Serebii":"voltorb"},{"Identifier":"0101","Name":"Electrode","IsShiny":true,"IsAvailable":true,"IsEmpty":false,"Serebii":"electrode"},{"Identifier":"0113","Name":"Chansey","IsShiny":true,"IsAvailable":true,"IsEmpty":false,"Serebii":"chansey"},{"Identifier":"0123","Name":"Scyther","IsShiny":true,"IsAvailable":true,"IsEmpty":false,"Serebii":"scyther"},{"Identifier":"0123-f","Name":"Scyther (Female)","IsShiny":true,"IsAvailable":true,"IsEmpty":false,"Serebii":"scyther"},{"Identifier":"0129","Name":"Magikarp","IsShiny":true,"IsAvailable":true,"IsEmpty":false,"Serebii":"magikarp"},{"Identifier":"0129-f","Name":"Magikarp (Female)","IsShiny":true,"IsAvailable":true,"IsEmpty":false,"Serebii":"magikarp"},{"Identifier":"0130","Name":"Gyarados","IsShiny":true,"IsAvailable":true,"IsEmpty":false,"Serebii":"gyarados"},{"Identifier":"0130-f","Name":"Gyarados (Female)","IsShiny":true,"IsAvailable":true,"IsEmpty":false,"Serebii":"gyarados"},{"Identifier":"0132","Name":"Ditto","IsShiny":true,"IsAvailable":true,"IsEmpty":false,"Serebii":"ditto"},{"Identifier":"0133","Name":"Eevee","IsShiny":true,"IsAvailable":true,"IsEmpty":false,"Serebii":"eevee"},{"Identifier":"0133-f","Name":"Eevee (Female)","IsShiny":true,"IsAvailable":true,"IsEmpty":false,"Serebii":"eevee"},{"Identifier":"0134","Name":"Vaporeon","IsShiny":true,"IsAvailable":true,"IsEmpty":false,"Serebii":"vaporeon"},{"Identifier":"0135","Name":"Jolteon","IsShiny":true,"IsAvailable":true,"IsEmpty":false,"Serebii":"jolteon"},{"Identifier":"0136","Name":"Flareon","IsShiny":true,"IsAvailable":true,"IsEmpty":false,"Serebii":"flareon"},{"Identifier":"0147","Name":"Dratini","IsShiny":true,"IsAvailable":true,"IsEmpty":false,"Serebii":"dratini"},{"Identifier":"0148","Name":"Dragonair","IsShiny":true,"IsAvailable":true,"IsEmpty":false,"Serebii":"dragonair"},{"Identifier":"0149","Name":"Dragonite","IsShiny":true,"IsAvailable":true,"IsEmpty":false,"Serebii":"dragonite"},{"Identifier":"0172","Name":"Pichu","IsShiny":true,"IsAvailable":true,"IsEmpty":false,"Serebii":"pichu"},{"Identifier":"0174","Name":"Igglybuff","IsShiny":true,"IsAvailable":true,"IsEmpty":false,"Serebii":"igglybuff"},{"Identifier":"0179","Name":"Mareep","IsShiny":true,"IsAvailable":true,"IsEmpty":false,"Serebii":"mareep"},{"Identifier":"0180","Name":"Flaaffy","IsShiny":true,"IsAvailable":true,"IsEmpty":false,"Serebii":"flaaffy"},{"Identifier":"0181","Name":"Ampharos","IsShiny":true,"IsAvailable":true,"IsEmpty":false,"Serebii":"ampharos"},{"Identifier":"0183","Name":"Marill","IsShiny":true,"IsAvailable":true,"IsEmpty":false,"Serebii":"marill"},{"Identifier":"0184","Name":"Azumarill","IsShiny":true,"IsAvailable":true,"IsEmpty":false,"Serebii":"azumarill"}]},{"BoxNumber":3,"Slots":[{"Identifier":"0185","Name":"Sudowoodo","IsShiny":true,"IsAvailable":true,"IsEmpty":false,"Serebii":"sudowoodo"},{"Identifier":"0185-f","Name":"Sudowoodo (Female)","IsShiny":true,"IsAvailable":true,"IsEmpty":false,"Serebii":"sudowoodo"},{"Identifier":"0187","Name":"Hoppip","IsShiny":true,"IsAvailable":true,"IsEmpty":false,"Serebii":"hoppip"},{"Identifier":"0188","Name":"Skiploom","IsShiny":true,"IsAvailable":true,"IsEmpty":false,"Serebii":"skiploom"},{"Identifier":"0189","Name":"Jumpluff","IsShiny":true,"IsAvailable":true,"IsEmpty":false,"Serebii":"jumpluff"},{"Identifier":"0191","Name":"Sunkern","IsShiny":true,"IsAvailable":true,"IsEmpty":false,"Serebii":"sunkern"},{"Identifier":"0192","Name":"Sunflora","IsShiny":true,"IsAvailable":true,"IsEmpty":false,"Serebii":"sunflora"},{"Identifier":"0194","Name":"Wooper","IsShiny":true,"IsAvailable":true,"IsEmpty":false,"Serebii":"wooper"},{"Identifier":"0194-f","Name":"Wooper (Female)","IsShiny":true,"IsAvailable":true,"IsEmpty":false,"Serebii":"wooper"},{"Identifier":"0195","Name":"Quagsire","IsShiny":true,"IsAvailable":true,"IsEmpty":false,"Serebii":"quagsire"},{"Identifier":"0195-f","Name":"Quagsire (Female)","IsShiny":true,"IsAvailable":true,"IsEmpty":false,"Serebii":"quagsire"},{"Identifier":"0196","Name":"Espeon","IsShiny":true,"IsAvailable":true,"IsEmpty":false,"Serebii":"espeon"},{"Identifier":"0197","Name":"Umbreon","IsShiny":true,"IsAvailable":true,"IsEmpty":false,"Serebii":"umbreon"},{"Identifier":"0198","Name":"Murkrow","IsShiny":true,"IsAvailable":true,"IsEmpty":false,"Serebii":"murkrow"},{"Identifier":"0198-f","Name":"Murkrow (Female)","IsShiny":true,"IsAvailable":true,"IsEmpty":false,"Serebii":"murkrow"},{"Identifier":"0199","Name":"Slowking","IsShiny":true,"IsAvailable":true,"IsEmpty":false,"Serebii":"slowking"},{"Identifier":"0200","Name":"Misdreavus","IsShiny":true,"IsAvailable":true,"IsEmpty":false,"Serebii":"misdreavus"},{"Identifier":"0203","Name":"Girafarig","IsShiny":true,"IsAvailable":true,"IsEmpty":false,"Serebii":"girafarig"},{"Identifier":"0203-f","Name":"Girafarig (Female)","IsShiny":true,"IsAvailable":true,"IsEmpty":false,"Serebii":"girafarig"},{"Identifier":"0204","Name":"Pineco","IsShiny":true,"IsAvailable":true,"IsEmpty":false,"Serebii":"pineco"},{"Identifier":"0205","Name":"Forretress","IsShiny":true,"IsAvailable":true,"IsEmpty":false,"Serebii":"forretress"},{"Identifier":"0206","Name":"Dunsparce","IsShiny":true,"IsAvailable":true,"IsEmpty":false,"Serebii":"dunsparce"},{"Identifier":"0211","Name":"Qwilfish","IsShiny":true,"IsAvailable":true,"IsEmpty":false,"Serebii":"qwilfish"},{"Identifier":"0212","Name":"Scizor","IsShiny":true,"IsAvailable":true,"IsEmpty":false,"Serebii":"scizor"},{"Identifier":"0212-f","Name":"Scizor (Female)","IsShiny":true,"IsAvailable":true,"IsEmpty":false,"Serebii":"scizor"},{"Identifier":"0214","Name":"Heracross","IsShiny":true,"IsAvailable":true,"IsEmpty":false,"Serebii":"heracross"},{"Identifier":"0214-f","Name":"Heracross (Female)","IsShiny":true,"IsAvailable":true,"IsEmpty":false,"Serebii":"heracross"},{"Identifier":"0215","Name":"Sneasel","IsShiny":true,"IsAvailable":true,"IsEmpty":false,"Serebii":"sneasel"},{"Identifier":"0215-f","Name":"Sneasel (Female)","IsShiny":true,"IsAvailable":true,"IsEmpty":false,"Serebii":"sneasel"},{"Identifier":"0216","Name":"Teddiursa","IsShiny":true,"IsAvailable":true,"IsEmpty":false,"Serebii":"teddiursa"}]},{"BoxNumber":4,"Slots":[{"Identifier":"0217","Name":"Ursaring","IsShiny":true,"IsAvailable":true,"IsEmpty":false,"Serebii":"ursaring"},{"Identifier":"0217-f","Name":"Ursaring (Female)","IsShiny":true,"IsAvailable":true,"IsEmpty":false,"Serebii":"ursaring"},{"Identifier":"0225","Name":"Delibird","IsShiny":true,"IsAvailable":true,"IsEmpty":false,"Serebii":"delibird"},{"Identifier":"0228","Name":"Houndour","IsShiny":true,"IsAvailable":true,"IsEmpty":false,"Serebii":"houndour"},{"Identifier":"0229","Name":"Houndoom","IsShiny":true,"IsAvailable":true,"IsEmpty":false,"Serebii":"houndoom"},{"Identifier":"0229-f","Name":"Houndoom (Female)","IsShiny":true,"IsAvailable":true,"IsEmpty":false,"Serebii":"houndoom"},{"Identifier":"0231","Name":"Phanpy","IsShiny":true,"IsAvailable":true,"IsEmpty":false,"Serebii":"phanpy"},{"Identifier":"0232","Name":"Donphan","IsShiny":true,"IsAvailable":true,"IsEmpty":false,"Serebii":"donphan"},{"Identifier":"0232-f","Name":"Donphan (Female)","IsShiny":true,"IsAvailable":true,"IsEmpty":false,"Serebii":"donphan"},{"Identifier":"0234","Name":"Stantler","IsShiny":true,"IsAvailable":true,"IsEmpty":false,"Serebii":"stantler"},{"Identifier":"0242","Name":"Blissey","IsShiny":true,"IsAvailable":true,"IsEmpty":false,"Serebii":"blissey"},{"Identifier":"0246","Name":"Larvitar","IsShiny":true,"IsAvailable":true,"IsEmpty":false,"Serebii":"larvitar"},{"Identifier":"0247","Name":"Pupitar","IsShiny":true,"IsAvailable":true,"IsEmpty":false,"Serebii":"pupitar"},{"Identifier":"0248","Name":"Tyranitar","IsShiny":true,"IsAvailable":true,"IsEmpty":false,"Serebii":"tyranitar"},{"Identifier":"0278","Name":"Wingull","IsShiny":true,"IsAvailable":true,"IsEmpty":false,"Serebii":"wingull"},{"Identifier":"0279","Name":"Pelipper","IsShiny":true,"IsAvailable":true,"IsEmpty":false,"Serebii":"pelipper"},{"Identifier":"0280","Name":"Ralts","IsShiny":true,"IsAvailable":true,"IsEmpty":false,"Serebii":"ralts"},{"Identifier":"0281","Name":"Kirlia","IsShiny":true,"IsAvailable":true,"IsEmpty":false,"Serebii":"kirlia"},{"Identifier":"0282","Name":"Gardevoir","IsShiny":true,"IsAvailable":true,"IsEmpty":false,"Serebii":"gardevoir"},{"Identifier":"0283","Name":"Surskit","IsShiny":true,"IsAvailable":true,"IsEmpty":false,"Serebii":"surskit"},{"Identifier":"0284","Name":"Masquerain","IsShiny":true,"IsAvailable":true,"IsEmpty":false,"Serebii":"masquerain"},{"Identifier":"0285","Name":"Shroomish","IsShiny":true,"IsAvailable":true,"IsEmpty":false,"Serebii":"shroomish"},{"Identifier":"0286","Name":"Breloom","IsShiny":true,"IsAvailable":true,"IsEmpty":false,"Serebii":"breloom"},{"Identifier":"0287","Name":"Slakoth","IsShiny":true,"IsAvailable":true,"IsEmpty":false,"Serebii":"slakoth"},{"Identifier":"0288","Name":"Vigoroth","IsShiny":true,"IsAvailable":true,"IsEmpty":false,"Serebii":"vigoroth"},{"Identifier":"0289","Name":"Slaking","IsShiny":true,"IsAvailable":true,"IsEmpty":false,"Serebii":"slaking"},{"Identifier":"0296","Name":"Makuhita","IsShiny":true,"IsAvailable":true,"IsEmpty":false,"Serebii":"makuhita"},{"Identifier":"0297","Name":"Hariyama","IsShiny":true,"IsAvailable":true,"IsEmpty":false,"Serebii":"hariyama"},{"Identifier":"0298","Name":"Azurill","IsShiny":true,"IsAvailable":true,"IsEmpty":false,"Serebii":"azurill"},{"Identifier":"0302","Name":"Sableye","IsShiny":true,"IsAvailable":true,"IsEmpty":false,"Serebii":"sableye"}]},{"BoxNumber":5,"Slots":[{"Identifier":"0307","Name":"Meditite","IsShiny":true,"IsAvailable":true,"IsEmpty":false,"Serebii":"meditite"},{"Identifier":"0307-f","Name":"Meditite (Female)","IsShiny":true,"IsAvailable":true,"IsEmpty":false,"Serebii":"meditite"},{"Identifier":"0308","Name":"Medicham","IsShiny":true,"IsAvailable":true,"IsEmpty":false,"Serebii":"medicham"},{"Identifier":"0308-f","Name":"Medicham (Female)","IsShiny":true,"IsAvailable":true,"IsEmpty":false,"Serebii":"medicham"},{"Identifier":"0316","Name":"Gulpin","IsShiny":true,"IsAvailable":true,"IsEmpty":false,"Serebii":"gulpin"},{"Identifier":"0316-f","Name":"Gulpin (Female)","IsShiny":true,"IsAvailable":true,"IsEmpty":false,"Serebii":"gulpin"},{"Identifier":"0317","Name":"Swalot","IsShiny":true,"IsAvailable":true,"IsEmpty":false,"Serebii":"swalot"},{"Identifier":"0317-f","Name":"Swalot (Female)","IsShiny":true,"IsAvailable":true,"IsEmpty":false,"Serebii":"swalot"},{"Identifier":"0322","Name":"Numel","IsShiny":true,"IsAvailable":true,"IsEmpty":false,"Serebii":"numel"},{"Identifier":"0322-f","Name":"Numel (Female)","IsShiny":true,"IsAvailable":true,"IsEmpty":false,"Serebii":"numel"},{"Identifier":"0323","Name":"Camerupt","IsShiny":true,"IsAvailable":true,"IsEmpty":false,"Serebii":"camerupt"},{"Identifier":"0323-f","Name":"Camerupt (Female)","IsShiny":true,"IsAvailable":true,"IsEmpty":false,"Serebii":"camerupt"},{"Identifier":"0324","Name":"Torkoal","IsShiny":true,"IsAvailable":true,"IsEmpty":false,"Serebii":"torkoal"},{"Identifier":"0325","Name":"Spoink","IsShiny":true,"IsAvailable":true,"IsEmpty":false,"Serebii":"spoink"},{"Identifier":"0326","Name":"Grumpig","IsShiny":true,"IsAvailable":true,"IsEmpty":false,"Serebii":"grumpig"},{"Identifier":"0331","Name":"Cacnea","IsShiny":true,"IsAvailable":true,"IsEmpty":false,"Serebii":"cacnea"},{"Identifier":"0332","Name":"Cacturne","IsShiny":true,"IsAvailable":true,"IsEmpty":false,"Serebii":"cacturne"},{"Identifier":"0332-f","Name":"Cacturne (Female)","IsShiny":true,"IsAvailable":true,"IsEmpty":false,"Serebii":"cacturne"},{"Identifier":"0333","Name":"Swablu","IsShiny":true,"IsAvailable":true,"IsEmpty":false,"Serebii":"swablu"},{"Identifier":"0334","Name":"Altaria","IsShiny":true,"IsAvailable":true,"IsEmpty":false,"Serebii":"altaria"},{"Identifier":"0335","Name":"Zangoose","IsShiny":true,"IsAvailable":true,"IsEmpty":false,"Serebii":"zangoose"},{"Identifier":"0336","Name":"Seviper","IsShiny":true,"IsAvailable":true,"IsEmpty":false,"Serebii":"seviper"},{"Identifier":"0339","Name":"Barboach","IsShiny":true,"IsAvailable":true,"IsEmpty":false,"Serebii":"barboach"},{"Identifier":"0340","Name":"Whiscash","IsShiny":true,"IsAvailable":true,"IsEmpty":false,"Serebii":"whiscash"},{"Identifier":"0353","Name":"Shuppet","IsShiny":true,"IsAvailable":true,"IsEmpty":false,"Serebii":"shuppet"},{"Identifier":"0354","Name":"Banette","IsShiny":true,"IsAvailable":true,"IsEmpty":false,"Serebii":"banette"},{"Identifier":"0357","Name":"Tropius","IsShiny":true,"IsAvailable":true,"IsEmpty":false,"Serebii":"tropius"},{"Identifier":"0361","Name":"Snorunt","IsShiny":true,"IsAvailable":true,"IsEmpty":false,"Serebii":"snorunt"},{"Identifier":"0362","Name":"Glalie","IsShiny":true,"IsAvailable":true,"IsEmpty":false,"Serebii":"glalie"},{"Identifier":"0370","Name":"Luvdisc","IsShiny":true,"IsAvailable":true,"IsEmpty":false,"Serebii":"luvdisc"}]},{"BoxNumber":6,"Slots":[{"Identifier":"0371","Name":"Bagon","IsShiny":true,"IsAvailable":true,"IsEmpty":false,"Serebii":"bagon"},{"Identifier":"0372","Name":"Shelgon","IsShiny":true,"IsAvailable":true,"IsEmpty":false,"Serebii":"shelgon"},{"Identifier":"0373","Name":"Salamence","IsShiny":true,"IsAvailable":true,"IsEmpty":false,"Serebii":"salamence"},{"Identifier":"0396","Name":"Starly","IsShiny":true,"IsAvailable":true,"IsEmpty":false,"Serebii":"starly"},{"Identifier":"0396-f","Name":"Starly (Female)","IsShiny":true,"IsAvailable":true,"IsEmpty":false,"Serebii":"starly"},{"Identifier":"0397","Name":"Staravia","IsShiny":true,"IsAvailable":true,"IsEmpty":false,"Serebii":"staravia"},{"Identifier":"0397-f","Name":"Staravia (Female)","IsShiny":true,"IsAvailable":true,"IsEmpty":false,"Serebii":"staravia"},{"Identifier":"0398","Name":"Staraptor","IsShiny":true,"IsAvailable":true,"IsEmpty":false,"Serebii":"staraptor"},{"Identifier":"0398-f","Name":"Staraptor (Female)","IsShiny":true,"IsAvailable":true,"IsEmpty":false,"Serebii":"staraptor"},{"Identifier":"0401","Name":"Kricketot","IsShiny":true,"IsAvailable":true,"IsEmpty":false,"Serebii":"kricketot"},{"Identifier":"0401-f","Name":"Kricketot (Female)","IsShiny":true,"IsAvailable":true,"IsEmpty":false,"Serebii":"kricketot"},{"Identifier":"0402","Name":"Kricketune","IsShiny":true,"IsAvailable":true,"IsEmpty":false,"Serebii":"kricketune"},{"Identifier":"0402-f","Name":"Kricketune (Female)","IsShiny":true,"IsAvailable":true,"IsEmpty":false,"Serebii":"kricketune"},{"Identifier":"0403","Name":"Shinx","IsShiny":true,"IsAvailable":true,"IsEmpty":false,"Serebii":"shinx"},{"Identifier":"0403-f","Name":"Shinx (Female)","IsShiny":true,"IsAvailable":true,"IsEmpty":false,"Serebii":"shinx"},{"Identifier":"0404","Name":"Luxio","IsShiny":true,"IsAvailable":true,"IsEmpty":false,"Serebii":"luxio"},{"Identifier":"0404-f","Name":"Luxio (Female)","IsShiny":true,"IsAvailable":true,"IsEmpty":false,"Serebii":"luxio"},{"Identifier":"0405","Name":"Luxray","IsShiny":true,"IsAvailable":true,"IsEmpty":false,"Serebii":"luxray"},{"Identifier":"0405-f","Name":"Luxray (Female)","IsShiny":true,"IsAvailable":true,"IsEmpty":false,"Serebii":"luxray"},{"Identifier":"0415","Name":"Combee","IsShiny":true,"IsAvailable":true,"IsEmpty":false,"Serebii":"combee"},{"Identifier":"0415-f","Name":"Combee (Female)","IsShiny":true,"IsAvailable":true,"IsEmpty":false,"Serebii":"combee"},{"Identifier":"0416","Name":"Vespiquen","IsShiny":true,"IsAvailable":true,"IsEmpty":false,"Serebii":"vespiquen"},{"Identifier":"0417","Name":"Pachirisu","IsShiny":true,"IsAvailable":true,"IsEmpty":false,"Serebii":"pachirisu"},{"Identifier":"0417-f","Name":"Pachirisu (Female)","IsShiny":true,"IsAvailable":true,"IsEmpty":false,"Serebii":"pachirisu"},{"Identifier":"0418","Name":"Buizel","IsShiny":true,"IsAvailable":true,"IsEmpty":false,"Serebii":"buizel"},{"Identifier":"0418-f","Name":"Buizel (Female)","IsShiny":true,"IsAvailable":true,"IsEmpty":false,"Serebii":"buizel"},{"Identifier":"0419","Name":"Floatzel","IsShiny":true,"IsAvailable":true,"IsEmpty":false,"Serebii":"floatzel"},{"Identifier":"0419-f","Name":"Floatzel (Female)","IsShiny":true,"IsAvailable":true,"IsEmpty":false,"Serebii":"floatzel"},{"Identifier":"0422","Name":"Shellos","IsShiny":true,"IsAvailable":true,"IsEmpty":false,"Serebii":"shellos"},{"Identifier":"0422-east","Name":"Shellos East Sea","IsShiny":true,"IsAvailable":true,"IsEmpty":false,"Serebii":"shellos"}]},{"BoxNumber":7,"Slots":[{"Identifier":"0423","Name":"Gastrodon","IsShiny":true,"IsAvailable":true,"IsEmpty":false,"Serebii":"gastrodon"},{"Identifier":"0423-east","Name":"Gastrodon East Sea","IsShiny":true,"IsAvailable":true,"IsEmpty":false,"Serebii":"gastrodon"},{"Identifier":"0425","Name":"Drifloon","IsShiny":true,"IsAvailable":true,"IsEmpty":false,"Serebii":"drifloon"},{"Identifier":"0426","Name":"Drifblim","IsShiny":true,"IsAvailable":true,"IsEmpty":false,"Serebii":"drifblim"},{"Identifier":"0429","Name":"Mismagius","IsShiny":true,"IsAvailable":true,"IsEmpty":false,"Serebii":"mismagius"},{"Identifier":"0430","Name":"Honchkrow","IsShiny":true,"IsAvailable":true,"IsEmpty":false,"Serebii":"honchkrow"},{"Identifier":"0434","Name":"Stunky","IsShiny":true,"IsAvailable":true,"IsEmpty":false,"Serebii":"stunky"},{"Identifier":"0435","Name":"Skuntank","IsShiny":true,"IsAvailable":true,"IsEmpty":false,"Serebii":"skuntank"},{"Identifier":"0436","Name":"Bronzor","IsShiny":true,"IsAvailable":true,"IsEmpty":false,"Serebii":"bronzor"},{"Identifier":"0437","Name":"Bronzong","IsShiny":true,"IsAvailable":true,"IsEmpty":false,"Serebii":"bronzong"},{"Identifier":"0438","Name":"Bonsly","IsShiny":true,"IsAvailable":true,"IsEmpty":false,"Serebii":"bonsly"},{"Identifier":"0440","Name":"Happiny","IsShiny":true,"IsAvailable":true,"IsEmpty":false,"Serebii":"happiny"},{"Identifier":"0442","Name":"Spiritomb","IsShiny":true,"IsAvailable":true,"IsEmpty":false,"Serebii":"spiritomb"},{"Identifier":"0443","Name":"Gible","IsShiny":true,"IsAvailable":true,"IsEmpty":false,"Serebii":"gible"},{"Identifier":"0443-f","Name":"Gible (Female)","IsShiny":true,"IsAvailable":true,"IsEmpty":false,"Serebii":"gible"},{"Identifier":"0444","Name":"Gabite","IsShiny":true,"IsAvailable":true,"IsEmpty":false,"Serebii":"gabite"},{"Identifier":"0444-f","Name":"Gabite (Female)","IsShiny":true,"IsAvailable":true,"IsEmpty":false,"Serebii":"gabite"},{"Identifier":"0445","Name":"Garchomp","IsShiny":true,"IsAvailable":true,"IsEmpty":false,"Serebii":"garchomp"},{"Identifier":"0445-f","Name":"Garchomp (Female)","IsShiny":true,"IsAvailable":true,"IsEmpty":false,"Serebii":"garchomp"},{"Identifier":"0447","Name":"Riolu","IsShiny":true,"IsAvailable":true,"IsEmpty":false,"Serebii":"riolu"},{"Identifier":"0448","Name":"Lucario","IsShiny":true,"IsAvailable":true,"IsEmpty":false,"Serebii":"lucario"},{"Identifier":"0449","Name":"Hippopotas","IsShiny":true,"IsAvailable":true,"IsEmpty":false,"Serebii":"hippopotas"},{"Identifier":"0449-f","Name":"Hippopotas (Female)","IsShiny":true,"IsAvailable":true,"IsEmpty":false,"Serebii":"hippopotas"},{"Identifier":"0450","Name":"Hippowdon","IsShiny":true,"IsAvailable":true,"IsEmpty":false,"Serebii":"hippowdon"},{"Identifier":"0450-f","Name":"Hippowdon (Female)","IsShiny":true,"IsAvailable":true,"IsEmpty":false,"Serebii":"hippowdon"},{"Identifier":"0453","Name":"Croagunk","IsShiny":true,"IsAvailable":true,"IsEmpty":false,"Serebii":"croagunk"},{"Identifier":"0453-f","Name":"Croagunk (Female)","IsShiny":true,"IsAvailable":true,"IsEmpty":false,"Serebii":"croagunk"},{"Identifier":"0454","Name":"Toxicroak","IsShiny":true,"IsAvailable":true,"IsEmpty":false,"Serebii":"toxicroak"},{"Identifier":"0454-f","Name":"Toxicroak (Female)","IsShiny":true,"IsAvailable":true,"IsEmpty":false,"Serebii":"toxicroak"},{"Identifier":"0456","Name":"Finneon","IsShiny":true,"IsAvailable":true,"IsEmpty":false,"Serebii":"finneon"}]},{"BoxNumber":8,"Slots":[{"Identifier":"0456-f","Name":"Finneon (Female)","IsShiny":true,"IsAvailable":true,"IsEmpty":false,"Serebii":"finneon"},{"Identifier":"0457","Name":"Lumineon","IsShiny":true,"IsAvailable":true,"IsEmpty":false,"Serebii":"lumineon"},{"Identifier":"0457-f","Name":"Lumineon (Female)","IsShiny":true,"IsAvailable":true,"IsEmpty":false,"Serebii":"lumineon"},{"Identifier":"0459","Name":"Snover","IsShiny":true,"IsAvailable":true,"IsEmpty":false,"Serebii":"snover"},{"Identifier":"0459-f","Name":"Snover (Female)","IsShiny":true,"IsAvailable":true,"IsEmpty":false,"Serebii":"snover"},{"Identifier":"0460","Name":"Abomasnow","IsShiny":true,"IsAvailable":true,"IsEmpty":false,"Serebii":"abomasnow"},{"Identifier":"0460-f","Name":"Abomasnow (Female)","IsShiny":true,"IsAvailable":true,"IsEmpty":false,"Serebii":"abomasnow"},{"Identifier":"0461","Name":"Weavile","IsShiny":true,"IsAvailable":true,"IsEmpty":false,"Serebii":"weavile"},{"Identifier":"0461-f","Name":"Weavile (Female)","IsShiny":true,"IsAvailable":true,"IsEmpty":false,"Serebii":"weavile"},{"Identifier":"0462","Name":"Magnezone","IsShiny":true,"IsAvailable":true,"IsEmpty":false,"Serebii":"magnezone"},{"Identifier":"0470","Name":"Leafeon","IsShiny":true,"IsAvailable":true,"IsEmpty":false,"Serebii":"leafeon"},{"Identifier":"0471","Name":"Glaceon","IsShiny":true,"IsAvailable":true,"IsEmpty":false,"Serebii":"glaceon"},{"Identifier":"0475","Name":"Gallade","IsShiny":true,"IsAvailable":true,"IsEmpty":false,"Serebii":"gallade"},{"Identifier":"0478","Name":"Froslass","IsShiny":true,"IsAvailable":true,"IsEmpty":false,"Serebii":"froslass"},{"Identifier":"0479","Name":"Rotom","IsShiny":true,"IsAvailable":true,"IsEmpty":false,"Serebii":"rotom"},{"Identifier":"0479-heat","Name":"Heat Rotom","IsShiny":true,"IsAvailable":true,"IsEmpty":false,"Serebii":"rotom"},{"Identifier":"0479-wash","Name":"Wash Rotom","IsShiny":true,"IsAvailable":true,"IsEmpty":false,"Serebii":"rotom"},{"Identifier":"0479-frost","Name":"Frost Rotom","IsShiny":true,"IsAvailable":true,"IsEmpty":false,"Serebii":"rotom"},{"Identifier":"0479-fan","Name":"Fan Rotom","IsShiny":true,"IsAvailable":true,"IsEmpty":false,"Serebii":"rotom"},{"Identifier":"0479-mow","Name":"Mow Rotom","IsShiny":true,"IsAvailable":true,"IsEmpty":false,"Serebii":"rotom"},{"Identifier":"0548","Name":"Petilil","IsShiny":true,"IsAvailable":true,"IsEmpty":false,"Serebii":"petilil"},{"Identifier":"0549","Name":"Lilligant","IsShiny":true,"IsAvailable":true,"IsEmpty":false,"Serebii":"lilligant"},{"Identifier":"0550","Name":"Basculin","IsShiny":true,"IsAvailable":true,"IsEmpty":false,"Serebii":"basculin"},{"Identifier":"0550-blue-striped","Name":"Basculin Blue-Striped Form","IsShiny":true,"IsAvailable":true,"IsEmpty":false,"Serebii":"basculin"},{"Identifier":"0551","Name":"Sandile","IsShiny":true,"IsAvailable":true,"IsEmpty":false,"Serebii":"sandile"},{"Identifier":"0552","Name":"Krokorok","IsShiny":true,"IsAvailable":true,"IsEmpty":false,"Serebii":"krokorok"},{"Identifier":"0553","Name":"Krookodile","IsShiny":true,"IsAvailable":true,"IsEmpty":false,"Serebii":"krookodile"},{"Identifier":"0570","Name":"Zorua","IsShiny":true,"IsAvailable":true,"IsEmpty":false,"Serebii":"zorua"},{"Identifier":"0571","Name":"Zoroark","IsShiny":true,"IsAvailable":true,"IsEmpty":false,"Serebii":"zoroark"},{"Identifier":"0574","Name":"Gothita","IsShiny":true,"IsAvailable":true,"IsEmpty":false,"Serebii":"gothita"}]},{"BoxNumber":9,"Slots":[{"Identifier":"0575","Name":"Gothorita","IsShiny":true,"IsAvailable":true,"IsEmpty":false,"Serebii":"gothorita"},{"Identifier":"0576","Name":"Gothitelle","IsShiny":true,"IsAvailable":true,"IsEmpty":false,"Serebii":"gothitelle"},{"Identifier":"0585","Name":"Deerling","IsShiny":true,"IsAvailable":true,"IsEmpty":false,"Serebii":"deerling"},{"Identifier":"0585-summer","Name":"Deerling Summer Form","IsShiny":true,"IsAvailable":true,"IsEmpty":false,"Serebii":"deerling"},{"Identifier":"0585-autumn","Name":"Deerling Autumn Form","IsShiny":true,"IsAvailable":true,"IsEmpty":false,"Serebii":"deerling"},{"Identifier":"0585-winter","Name":"Deerling Winter Form","IsShiny":true,"IsAvailable":true,"IsEmpty":false,"Serebii":"deerling"},{"Identifier":"0586","Name":"Sawsbuck","IsShiny":true,"IsAvailable":true,"IsEmpty":false,"Serebii":"sawsbuck"},{"Identifier":"0586-summer","Name":"Sawsbuck Summer Form","IsShiny":true,"IsAvailable":true,"IsEmpty":false,"Serebii":"sawsbuck"},{"Identifier":"0586-autumn","Name":"Sawsbuck Autumn Form","IsShiny":true,"IsAvailable":true,"IsEmpty":false,"Serebii":"sawsbuck"},{"Identifier":"0586-winter","Name":"Sawsbuck Winter Form","IsShiny":true,"IsAvailable":true,"IsEmpty":false,"Serebii":"sawsbuck"},{"Identifier":"0590","Name":"Foongus","IsShiny":true,"IsAvailable":true,"IsEmpty":false,"Serebii":"foongus"},{"Identifier":"0591","Name":"Amoonguss","IsShiny":true,"IsAvailable":true,"IsEmpty":false,"Serebii":"amoonguss"},{"Identifier":"0594","Name":"Alomomola","IsShiny":true,"IsAvailable":true,"IsEmpty":false,"Serebii":"alomomola"},{"Identifier":"0602","Name":"Tynamo","IsShiny":true,"IsAvailable":true,"IsEmpty":false,"Serebii":"tynamo"},{"Identifier":"0603","Name":"Eelektrik","IsShiny":true,"IsAvailable":true,"IsEmpty":false,"Serebii":"eelektrik"},{"Identifier":"0604","Name":"Eelektross","IsShiny":true,"IsAvailable":true,"IsEmpty":false,"Serebii":"eelektross"},{"Identifier":"0610","Name":"Axew","IsShiny":true,"IsAvailable":true,"IsEmpty":false,"Serebii":"axew"},{"Identifier":"0611","Name":"Fraxure","IsShiny":true,"IsAvailable":true,"IsEmpty":false,"Serebii":"fraxure"},{"Identifier":"0612","Name":"Haxorus","IsShiny":true,"IsAvailable":true,"IsEmpty":false,"Serebii":"haxorus"},{"Identifier":"0613","Name":"Cubchoo","IsShiny":true,"IsAvailable":true,"IsEmpty":false,"Serebii":"cubchoo"},{"Identifier":"0614","Name":"Beartic","IsShiny":true,"IsAvailable":true,"IsEmpty":false,"Serebii":"beartic"},{"Identifier":"0615","Name":"Cryogonal","IsShiny":true,"IsAvailable":true,"IsEmpty":false,"Serebii":"cryogonal"},{"Identifier":"0624","Name":"Pawniard","IsShiny":true,"IsAvailable":true,"IsEmpty":false,"Serebii":"pawniard"},{"Identifier":"0625","Name":"Bisharp","IsShiny":true,"IsAvailable":true,"IsEmpty":false,"Serebii":"bisharp"},{"Identifier":"0627","Name":"Rufflet","IsShiny":true,"IsAvailable":true,"IsEmpty":false,"Serebii":"rufflet"},{"Identifier":"0628","Name":"Braviary","IsShiny":true,"IsAvailable":true,"IsEmpty":false,"Serebii":"braviary"},{"Identifier":"0633","Name":"Deino","IsShiny":true,"IsAvailable":true,"IsEmpty":false,"Serebii":"deino"},{"Identifier":"0634","Name":"Zweilous","IsShiny":true,"IsAvailable":true,"IsEmpty":false,"Serebii":"zweilous"},{"Identifier":"0635","Name":"Hydreigon","IsShiny":true,"IsAvailable":true,"IsEmpty":false,"Serebii":"hydreigon"},{"Identifier":"0636","Name":"Larvesta","IsShiny":true,"IsAvailable":true,"IsEmpty":false,"Serebii":"larvesta"}]},{"BoxNumber":10,"Slots":[{"Identifier":"0637","Name":"Volcarona","IsShiny":true,"IsAvailable":true,"IsEmpty":false,"Serebii":"volcarona"},{"Identifier":"0656","Name":"Froakie","IsShiny":true,"IsAvailable":true,"IsEmpty":false,"Serebii":"froakie"},{"Identifier":"0657","Name":"Frogadier","IsShiny":true,"IsAvailable":true,"IsEmpty":false,"Serebii":"frogadier"},{"Identifier":"0658","Name":"Greninja","IsShiny":true,"IsAvailable":true,"IsEmpty":false,"Serebii":"greninja"},{"Identifier":"0661","Name":"Fletchling","IsShiny":true,"IsAvailable":true,"IsEmpty":false,"Serebii":"fletchling"},{"Identifier":"0662","Name":"Fletchinder","IsShiny":true,"IsAvailable":true,"IsEmpty":false,"Serebii":"fletchinder"},{"Identifier":"0663","Name":"Talonflame","IsShiny":true,"IsAvailable":true,"IsEmpty":false,"Serebii":"talonflame"},{"Identifier":"0664","Name":"Scatterbug","IsShiny":true,"IsAvailable":true,"IsEmpty":false,"Serebii":"scatterbug"},{"Identifier":"0665","Name":"Spewpa","IsShiny":true,"IsAvailable":true,"IsEmpty":false,"Serebii":"spewpa"},{"Identifier":"0666","Name":"Vivillon","IsShiny":true,"IsAvailable":true,"IsEmpty":false,"Serebii":"vivillon"},{"Identifier":"0666-meadow","Name":"Vivillon Meadow Pattern","IsShiny":true,"IsAvailable":true,"IsEmpty":false,"Serebii":"vivillon"},{"Identifier":"0666-polar","Name":"Vivillon Polar Pattern","IsShiny":true,"IsAvailable":true,"IsEmpty":false,"Serebii":"vivillon"},{"Identifier":"0666-tundra","Name":"Vivillon Tundra Pattern","IsShiny":true,"IsAvailable":true,"IsEmpty":false,"Serebii":"vivillon"},{"Identifier":"0666-continental","Name":"Vivillon Continental Pattern","IsShiny":true,"IsAvailable":true,"IsEmpty":false,"Serebii":"vivillon"},{"Identifier":"0666-garden","Name":"Vivillon Garden Pattern","IsShiny":true,"IsAvailable":true,"IsEmpty":false,"Serebii":"vivillon"},{"Identifier":"0666-elegant","Name":"Vivillon Elegant Pattern","IsShiny":true,"IsAvailable":true,"IsEmpty":false,"Serebii":"vivillon"},{"Identifier":"0666-modern","Name":"Vivillon Modern Pattern","IsShiny":true,"IsAvailable":true,"IsEmpty":false,"Serebii":"vivillon"},{"Identifier":"0666-marine","Name":"Vivillon Marine Pattern","IsShiny":true,"IsAvailable":true,"IsEmpty":false,"Serebii":"vivillon"},{"Identifier":"0666-archipelago","Name":"Vivillon Archipelago Pattern","IsShiny":true,"IsAvailable":true,"IsEmpty":false,"Serebii":"vivillon"},{"Identifier":"0666-high-plains","Name":"Vivillon High Plains Pattern","IsShiny":true,"IsAvailable":true,"IsEmpty":false,"Serebii":"vivillon"},{"Identifier":"0666-sandstorm","Name":"Vivillon Sandstorm Pattern","IsShiny":true,"IsAvailable":true,"IsEmpty":false,"Serebii":"vivillon"},{"Identifier":"0666-river","Name":"Vivillon River Pattern","IsShiny":true,"IsAvailable":true,"IsEmpty":false,"Serebii":"vivillon"},{"Identifier":"0666-monsoon","Name":"Vivillon Monsoon Pattern","IsShiny":true,"IsAvailable":true,"IsEmpty":false,"Serebii":"vivillon"},{"Identifier":"0666-savanna","Name":"Vivillon Savanna Pattern","IsShiny":true,"IsAvailable":true,"IsEmpty":false,"Serebii":"vivillon"},{"Identifier":"0666-sun","Name":"Vivillon Sun Pattern","IsShiny":true,"IsAvailable":true,"IsEmpty":false,"Serebii":"vivillon"},{"Identifier":"0666-ocean","Name":"Vivillon Ocean Pattern","IsShiny":true,"IsAvailable":true,"IsEmpty":false,"Serebii":"vivillon"},{"Identifier":"0666-jungle","Name":"Vivillon Jungle Pattern","IsShiny":true,"IsAvailable":true,"IsEmpty":false,"Serebii":"vivillon"},{"Identifier":"0666-fancy","Name":"Vivillon Fancy Pattern","IsShiny":true,"IsAvailable":true,"IsEmpty":false,"Serebii":"vivillon"},{"Identifier":"0667","Name":"Litleo","IsShiny":true,"IsAvailable":true,"IsEmpty":false,"Serebii":"litleo"},{"Identifier":"0668","Name":"Pyroar","IsShiny":true,"IsAvailable":true,"IsEmpty":false,"Serebii":"pyroar"}]},{"BoxNumber":11,"Slots":[{"Identifier":"0668-f","Name":"Pyroar (Female)","IsShiny":true,"IsAvailable":true,"IsEmpty":false,"Serebii":"pyroar"},{"Identifier":"0669","Name":"Flabébé","IsShiny":true,"IsAvailable":true,"IsEmpty":false,"Serebii":"flabebe"},{"Identifier":"0669-blue","Name":"Flabébé Blue Flower","IsShiny":true,"IsAvailable":true,"IsEmpty":false,"Serebii":"flabebe"},{"Identifier":"0669-orange","Name":"Flabébé Orange Flower","IsShiny":true,"IsAvailable":true,"IsEmpty":false,"Serebii":"flabebe"},{"Identifier":"0669-white","Name":"Flabébé White Flower","IsShiny":true,"IsAvailable":true,"IsEmpty":false,"Serebii":"flabebe"},{"Identifier":"0669-yellow","Name":"Flabébé Yellow Flower","IsShiny":true,"IsAvailable":true,"IsEmpty":false,"Serebii":"flabebe"},{"Identifier":"0670","Name":"Floette","IsShiny":true,"IsAvailable":true,"IsEmpty":false,"Serebii":"floette"},{"Identifier":"0670-blue","Name":"Floette Blue Flower","IsShiny":true,"IsAvailable":true,"IsEmpty":false,"Serebii":"floette"},{"Identifier":"0670-orange","Name":"Floette Orange Flower","IsShiny":true,"IsAvailable":true,"IsEmpty":false,"Serebii":"floette"},{"Identifier":"0670-white","Name":"Floette White Flower","IsShiny":true,"IsAvailable":true,"IsEmpty":false,"Serebii":"floette"},{"Identifier":"0670-yellow","Name":"Floette Yellow Flower","IsShiny":true,"IsAvailable":true,"IsEmpty":false,"Serebii":"floette"},{"Identifier":"0671","Name":"Florges","IsShiny":true,"IsAvailable":true,"IsEmpty":false,"Serebii":"florges"},{"Identifier":"0671-blue","Name":"Florges Blue Flower","IsShiny":true,"IsAvailable":true,"IsEmpty":false,"Serebii":"florges"},{"Identifier":"0671-orange","Name":"Florges Orange Flower","IsShiny":true,"IsAvailable":true,"IsEmpty":false,"Serebii":"florges"},{"Identifier":"0671-white","Name":"Florges White Flower","IsShiny":true,"IsAvailable":true,"IsEmpty":false,"Serebii":"florges"},{"Identifier":"0671-yellow","Name":"Florges Yellow Flower","IsShiny":true,"IsAvailable":true,"IsEmpty":false,"Serebii":"florges"},{"Identifier":"0672","Name":"Skiddo","IsShiny":true,"IsAvailable":true,"IsEmpty":false,"Serebii":"skiddo"},{"Identifier":"0673","Name":"Gogoat","IsShiny":true,"IsAvailable":true,"IsEmpty":false,"Serebii":"gogoat"},{"Identifier":"0690","Name":"Skrelp","IsShiny":true,"IsAvailable":true,"IsEmpty":false,"Serebii":"skrelp"},{"Identifier":"0691","Name":"Dragalge","IsShiny":true,"IsAvailable":true,"IsEmpty":false,"Serebii":"dragalge"},{"Identifier":"0692","Name":"Clauncher","IsShiny":true,"IsAvailable":true,"IsEmpty":false,"Serebii":"clauncher"},{"Identifier":"0693","Name":"Clawitzer","IsShiny":true,"IsAvailable":true,"IsEmpty":false,"Serebii":"clawitzer"},{"Identifier":"0700","Name":"Sylveon","IsShiny":true,"IsAvailable":true,"IsEmpty":false,"Serebii":"sylveon"},{"Identifier":"0701","Name":"Hawlucha","IsShiny":true,"IsAvailable":true,"IsEmpty":false,"Serebii":"hawlucha"},{"Identifier":"0702","Name":"Dedenne","IsShiny":true,"IsAvailable":true,"IsEmpty":false,"Serebii":"dedenne"},{"Identifier":"0704","Name":"Goomy","IsShiny":true,"IsAvailable":true,"IsEmpty":false,"Serebii":"goomy"},{"Identifier":"0705","Name":"Sliggoo","IsShiny":true,"IsAvailable":true,"IsEmpty":false,"Serebii":"sliggoo"},{"Identifier":"0706","Name":"Goodra","IsShiny":true,"IsAvailable":true,"IsEmpty":false,"Serebii":"goodra"},{"Identifier":"0707","Name":"Klefki","IsShiny":true,"IsAvailable":true,"IsEmpty":false,"Serebii":"klefki"},{"Identifier":"0712","Name":"Bergmite","IsShiny":true,"IsAvailable":true,"IsEmpty":false,"Serebii":"bergmite"}]},{"BoxNumber":12,"Slots":[{"Identifier":"0713","Name":"Avalugg","IsShiny":true,"IsAvailable":true,"IsEmpty":false,"Serebii":"avalugg"},{"Identifier":"0714","Name":"Noibat","IsShiny":true,"IsAvailable":true,"IsEmpty":false,"Serebii":"noibat"},{"Identifier":"0715","Name":"Noivern","IsShiny":true,"IsAvailable":true,"IsEmpty":false,"Serebii":"noivern"},{"Identifier":"0734","Name":"Yungoos","IsShiny":true,"IsAvailable":true,"IsEmpty":false,"Serebii":"yungoos"},{"Identifier":"0735","Name":"Gumshoos","IsShiny":true,"IsAvailable":true,"IsEmpty":false,"Serebii":"gumshoos"},{"Identifier":"0739","Name":"Crabrawler","IsShiny":true,"IsAvailable":true,"IsEmpty":false,"Serebii":"crabrawler"},{"Identifier":"0740","Name":"Crabominable","IsShiny":true,"IsAvailable":true,"IsEmpty":false,"Serebii":"crabominable"},{"Identifier":"0741","Name":"Oricorio","IsShiny":true,"IsAvailable":true,"IsEmpty":false,"Serebii":"oricorio"},{"Identifier":"0741-pom-pom","Name":"Oricorio Pom-Pom Style","IsShiny":true,"IsAvailable":true,"IsEmpty":false,"Serebii":"oricorio"},{"Identifier":"0741-pau","Name":"Oricorio Pa'u Style","IsShiny":true,"IsAvailable":true,"IsEmpty":false,"Serebii":"oricorio"},{"Identifier":"0741-sensu","Name":"Oricorio Sensu Style","IsShiny":true,"IsAvailable":true,"IsEmpty":false,"Serebii":"oricorio"},{"Identifier":"0744","Name":"Rockruff","IsShiny":true,"IsAvailable":true,"IsEmpty":false,"Serebii":"rockruff"},{"Identifier":"0744--own-tempo","Name":"Rockruff (Own Tempo Ability)","IsShiny":true,"IsAvailable":true,"IsEmpty":false,"Serebii":"rockruff"},{"Identifier":"0745","Name":"Lycanroc","IsShiny":true,"IsAvailable":true,"IsEmpty":false,"Serebii":"lycanroc"},{"Identifier":"0745-midnight","Name":"Lycanroc Midnight Form","IsShiny":true,"IsAvailable":true,"IsEmpty":false,"Serebii":"lycanroc"},{"Identifier":"0745-dusk","Name":"Lycanroc Dusk Form","IsShiny":true,"IsAvailable":true,"IsEmpty":false,"Serebii":"lycanroc"},{"Identifier":"0747","Name":"Mareanie","IsShiny":true,"IsAvailable":true,"IsEmpty":false,"Serebii":"mareanie"},{"Identifier":"0748","Name":"Toxapex","IsShiny":true,"IsAvailable":true,"IsEmpty":false,"Serebii":"toxapex"},{"Identifier":"0749","Name":"Mudbray","IsShiny":true,"IsAvailable":true,"IsEmpty":false,"Serebii":"mudbray"},{"Identifier":"0750","Name":"Mudsdale","IsShiny":true,"IsAvailable":true,"IsEmpty":false,"Serebii":"mudsdale"},{"Identifier":"0753","Name":"Fomantis","IsShiny":true,"IsAvailable":true,"IsEmpty":false,"Serebii":"fomantis"},{"Identifier":"0754","Name":"Lurantis","IsShiny":true,"IsAvailable":true,"IsEmpty":false,"Serebii":"lurantis"},{"Identifier":"0757","Name":"Salandit","IsShiny":true,"IsAvailable":true,"IsEmpty":false,"Serebii":"salandit"},{"Identifier":"0758","Name":"Salazzle","IsShiny":true,"IsAvailable":true,"IsEmpty":false,"Serebii":"salazzle"},{"Identifier":"0761","Name":"Bounsweet","IsShiny":true,"IsAvailable":true,"IsEmpty":false,"Serebii":"bounsweet"},{"Identifier":"0762","Name":"Steenee","IsShiny":true,"IsAvailable":true,"IsEmpty":false,"Serebii":"steenee"},{"Identifier":"0763","Name":"Tsareena","IsShiny":true,"IsAvailable":true,"IsEmpty":false,"Serebii":"tsareena"},{"Identifier":"0765","Name":"Oranguru","IsShiny":true,"IsAvailable":true,"IsEmpty":false,"Serebii":"oranguru"},{"Identifier":"0766","Name":"Passimian","IsShiny":true,"IsAvailable":true,"IsEmpty":false,"Serebii":"passimian"},{"Identifier":"0769","Name":"Sandygast","IsShiny":true,"IsAvailable":true,"IsEmpty":false,"Serebii":"sandygast"}]},{"BoxNumber":13,"Slots":[{"Identifier":"0770","Name":"Palossand","IsShiny":true,"IsAvailable":true,"IsEmpty":false,"Serebii":"palossand"},{"Identifier":"0775","Name":"Komala","IsShiny":true,"IsAvailable":true,"IsEmpty":false,"Serebii":"komala"},{"Identifier":"0778","Name":"Mimikyu","IsShiny":true,"IsAvailable":true,"IsEmpty":false,"Serebii":"mimikyu"},{"Identifier":"0779","Name":"Bruxish","IsShiny":true,"IsAvailable":true,"IsEmpty":false,"Serebii":"bruxish"},{"Identifier":"0813","Name":"Scorbunny","IsShiny":true,"IsAvailable":true,"IsEmpty":false,"Serebii":"scorbunny"},{"Identifier":"0814","Name":"Raboot","IsShiny":true,"IsAvailable":true,"IsEmpty":false,"Serebii":"raboot"},{"Identifier":"0815","Name":"Cinderace","IsShiny":true,"IsAvailable":true,"IsEmpty":false,"Serebii":"cinderace"},{"Identifier":"0819","Name":"Skwovet","IsShiny":true,"IsAvailable":true,"IsEmpty":false,"Serebii":"skwovet"},{"Identifier":"0820","Name":"Greedent","IsShiny":true,"IsAvailable":true,"IsEmpty":false,"Serebii":"greedent"},{"Identifier":"0821","Name":"Rookidee","IsShiny":true,"IsAvailable":true,"IsEmpty":false,"Serebii":"rookidee"},{"Identifier":"0822","Name":"Corvisquire","IsShiny":true,"IsAvailable":true,"IsEmpty":false,"Serebii":"corvisquire"},{"Identifier":"0823","Name":"Corviknight","IsShiny":true,"IsAvailable":true,"IsEmpty":false,"Serebii":"corviknight"},{"Identifier":"0833","Name":"Chewtle","IsShiny":true,"IsAvailable":true,"IsEmpty":false,"Serebii":"chewtle"},{"Identifier":"0834","Name":"Drednaw","IsShiny":true,"IsAvailable":true,"IsEmpty":false,"Serebii":"drednaw"},{"Identifier":"0837","Name":"Rolycoly","IsShiny":true,"IsAvailable":true,"IsEmpty":false,"Serebii":"rolycoly"},{"Identifier":"0838","Name":"Carkol","IsShiny":true,"IsAvailable":true,"IsEmpty":false,"Serebii":"carkol"},{"Identifier":"0839","Name":"Coalossal","IsShiny":true,"IsAvailable":true,"IsEmpty":false,"Serebii":"coalossal"},{"Identifier":"0840","Name":"Applin","IsShiny":true,"IsAvailable":true,"IsEmpty":false,"Serebii":"applin"},{"Identifier":"0841","Name":"Flapple","IsShiny":true,"IsAvailable":true,"IsEmpty":false,"Serebii":"flapple"},{"Identifier":"0842","Name":"Appletun","IsShiny":true,"IsAvailable":true,"IsEmpty":false,"Serebii":"appletun"},{"Identifier":"0843","Name":"Silicobra","IsShiny":true,"IsAvailable":true,"IsEmpty":false,"Serebii":"silicobra"},{"Identifier":"0844","Name":"Sandaconda","IsShiny":true,"IsAvailable":true,"IsEmpty":false,"Serebii":"sandaconda"},{"Identifier":"0846","Name":"Arrokuda","IsShiny":true,"IsAvailable":true,"IsEmpty":false,"Serebii":"arrokuda"},{"Identifier":"0847","Name":"Barraskewda","IsShiny":true,"IsAvailable":true,"IsEmpty":false,"Serebii":"barraskewda"},{"Identifier":"0848","Name":"Toxel","IsShiny":true,"IsAvailable":true,"IsEmpty":false,"Serebii":"toxel"},{"Identifier":"0849","Name":"Toxtricity","IsShiny":true,"IsAvailable":true,"IsEmpty":false,"Serebii":"toxtricity"},{"Identifier":"0849-low-key","Name":"Toxtricity Low Key Form","IsShiny":true,"IsAvailable":true,"IsEmpty":false,"Serebii":"toxtricity"},{"Identifier":"0854","Name":"Sinistea","IsShiny":true,"IsAvailable":true,"IsEmpty":false,"Serebii":"sinistea"},{"Identifier":"0854-antique","Name":"Sinistea (Antique)","IsShiny":true,"IsAvailable":true,"IsEmpty":false,"Serebii":"sinistea"},{"Identifier":"0855","Name":"Polteageist","IsShiny":true,"IsAvailable":true,"IsEmpty":false,"Serebii":"polteageist"}]},{"BoxNumber":14,"Slots":[{"Identifier":"0855-antique","Name":"Polteageist (Antique)","IsShiny":true,"IsAvailable":true,"IsEmpty":false,"Serebii":"polteageist"},{"Identifier":"0856","Name":"Hatenna","IsShiny":true,"IsAvailable":true,"IsEmpty":false,"Serebii":"hatenna"},{"Identifier":"0857","Name":"Hattrem","IsShiny":true,"IsAvailable":true,"IsEmpty":false,"Serebii":"hattrem"},{"Identifier":"0858","Name":"Hatterene","IsShiny":true,"IsAvailable":true,"IsEmpty":false,"Serebii":"hatterene"},{"Identifier":"0859","Name":"Impidimp","IsShiny":true,"IsAvailable":true,"IsEmpty":false,"Serebii":"impidimp"},{"Identifier":"0860","Name":"Morgrem","IsShiny":true,"IsAvailable":true,"IsEmpty":false,"Serebii":"morgrem"},{"Identifier":"0861","Name":"Grimmsnarl","IsShiny":true,"IsAvailable":true,"IsEmpty":false,"Serebii":"grimmsnarl"},{"Identifier":"0863","Name":"Perrserker","IsShiny":true,"IsAvailable":true,"IsEmpty":false,"Serebii":"perrserker"},{"Identifier":"0870","Name":"Falinks","IsShiny":true,"IsAvailable":true,"IsEmpty":false,"Serebii":"falinks"},{"Identifier":"0871","Name":"Pincurchin","IsShiny":true,"IsAvailable":true,"IsEmpty":false,"Serebii":"pincurchin"},{"Identifier":"0872","Name":"Snom","IsShiny":true,"IsAvailable":true,"IsEmpty":false,"Serebii":"snom"},{"Identifier":"0873","Name":"Frosmoth","IsShiny":true,"IsAvailable":true,"IsEmpty":false,"Serebii":"frosmoth"},{"Identifier":"0874","Name":"Stonjourner","IsShiny":true,"IsAvailable":true,"IsEmpty":false,"Serebii":"stonjourner"},{"Identifier":"0875","Name":"Eiscue","IsShiny":true,"IsAvailable":true,"IsEmpty":false,"Serebii":"eiscue"},{"Identifier":"0876","Name":"Indeedee","IsShiny":true,"IsAvailable":true,"IsEmpty":false,"Serebii":"indeedee"},{"Identifier":"0876-f","Name":"Female Indeedee","IsShiny":true,"IsAvailable":true,"IsEmpty":false,"Serebii":"indeedee"},{"Identifier":"0878","Name":"Cufant","IsShiny":true,"IsAvailable":true,"IsEmpty":false,"Serebii":"cufant"},{"Identifier":"0879","Name":"Copperajah","IsShiny":true,"IsAvailable":true,"IsEmpty":false,"Serebii":"copperajah"},{"Identifier":"0885","Name":"Dreepy","IsShiny":true,"IsAvailable":true,"IsEmpty":false,"Serebii":"dreepy"},{"Identifier":"0886","Name":"Drakloak","IsShiny":true,"IsAvailable":true,"IsEmpty":false,"Serebii":"drakloak"},{"Identifier":"0887","Name":"Dragapult","IsShiny":true,"IsAvailable":true,"IsEmpty":false,"Serebii":"dragapult"},{"Identifier":"0906","Name":"Sprigatito","IsShiny":true,"IsAvailable":true,"IsEmpty":false,"Serebii":"sprigatito"},{"Identifier":"0907","Name":"Floragato","IsShiny":true,"IsAvailable":true,"IsEmpty":false,"Serebii":"floragato"},{"Identifier":"0908","Name":"Meowscarada","IsShiny":true,"IsAvailable":true,"IsEmpty":false,"Serebii":"meowscarada"},{"Identifier":"0909","Name":"Fuecoco","IsShiny":true,"IsAvailable":true,"IsEmpty":false,"Serebii":"fuecoco"},{"Identifier":"0910","Name":"Crocalor","IsShiny":true,"IsAvailable":true,"IsEmpty":false,"Serebii":"crocalor"},{"Identifier":"0911","Name":"Skeledirge","IsShiny":true,"IsAvailable":true,"IsEmpty":false,"Serebii":"skeledirge"},{"Identifier":"0912","Name":"Quaxly","IsShiny":true,"IsAvailable":true,"IsEmpty":false,"Serebii":"quaxly"},{"Identifier":"0913","Name":"Quaxwell","IsShiny":true,"IsAvailable":true,"IsEmpty":false,"Serebii":"quaxwell"},{"Identifier":"0914","Name":"Quaquaval","IsShiny":true,"IsAvailable":true,"IsEmpty":false,"Serebii":"quaquaval"}]},{"BoxNumber":15,"Slots":[{"Identifier":"0915","Name":"Lechonk","IsShiny":true,"IsAvailable":true,"IsEmpty":false,"Serebii":"lechonk"},{"Identifier":"0916","Name":"Oinkologne","IsShiny":true,"IsAvailable":true,"IsEmpty":false,"Serebii":"oinkologne"},{"Identifier":"0916-f","Name":"Oinkologne (Female)","IsShiny":true,"IsAvailable":true,"IsEmpty":false,"Serebii":"Oinkologne"},{"Identifier":"0917","Name":"Tarountula","IsShiny":true,"IsAvailable":true,"IsEmpty":false,"Serebii":"tarountula"},{"Identifier":"0918","Name":"Spidops","IsShiny":true,"IsAvailable":true,"IsEmpty":false,"Serebii":"spidops"},{"Identifier":"0919","Name":"Nymble","IsShiny":true,"IsAvailable":true,"IsEmpty":false,"Serebii":"nymble"},{"Identifier":"0920","Name":"Lokix","IsShiny":true,"IsAvailable":true,"IsEmpty":false,"Serebii":"lokix"},{"Identifier":"0921","Name":"Pawmi","IsShiny":true,"IsAvailable":true,"IsEmpty":false,"Serebii":"pawmi"},{"Identifier":"0922","Name":"Pawmo","IsShiny":true,"IsAvailable":true,"IsEmpty":false,"Serebii":"pawmo"},{"Identifier":"0923","Name":"Pawmot","IsShiny":true,"IsAvailable":true,"IsEmpty":false,"Serebii":"pawmot"},{"Identifier":"0924","Name":"Tandemaus","IsShiny":true,"IsAvailable":true,"IsEmpty":false,"Serebii":"tandemaus"},{"Identifier":"0925","Name":"Maushold","IsShiny":true,"IsAvailable":true,"IsEmpty":false,"Serebii":"maushold"},{"Identifier":"0925-four","Name":"Maushold Family of Four","IsShiny":true,"IsAvailable":true,"IsEmpty":false,"Serebii":"Maushold"},{"Identifier":"0926","Name":"Fidough","IsShiny":true,"IsAvailable":true,"IsEmpty":false,"Serebii":"fidough"},{"Identifier":"0927","Name":"Dachsbun","IsShiny":true,"IsAvailable":true,"IsEmpty":false,"Serebii":"dachsbun"},{"Identifier":"0928","Name":"Smoliv","IsShiny":true,"IsAvailable":true,"IsEmpty":false,"Serebii":"smoliv"},{"Identifier":"0929","Name":"Dolliv","IsShiny":true,"IsAvailable":true,"IsEmpty":false,"Serebii":"dolliv"},{"Identifier":"0930","Name":"Arboliva","IsShiny":true,"IsAvailable":true,"IsEmpty":false,"Serebii":"arboliva"},{"Identifier":"0931","Name":"Squawkabilly","IsShiny":true,"IsAvailable":true,"IsEmpty":false,"Serebii":"squawkabilly"},{"Identifier":"0931-blue","Name":"Squawkabilly Blue-feathered","IsShiny":true,"IsAvailable":true,"IsEmpty":false,"Serebii":"Squawkabilly"},{"Identifier":"0931-yellow","Name":"Squawkabilly Yellow-feathered","IsShiny":true,"IsAvailable":true,"IsEmpty":false,"Serebii":"Squawkabilly"},{"Identifier":"0931-white","Name":"Squawkabilly White-feathered","IsShiny":true,"IsAvailable":true,"IsEmpty":false,"Serebii":"Squawkabilly"},{"Identifier":"0932","Name":"Nacli","IsShiny":true,"IsAvailable":true,"IsEmpty":false,"Serebii":"nacli"},{"Identifier":"0933","Name":"Naclstack","IsShiny":true,"IsAvailable":true,"IsEmpty":false,"Serebii":"naclstack"},{"Identifier":"0934","Name":"Garganacl","IsShiny":true,"IsAvailable":true,"IsEmpty":false,"Serebii":"garganacl"},{"Identifier":"0935","Name":"Charcadet","IsShiny":true,"IsAvailable":true,"IsEmpty":false,"Serebii":"charcadet"},{"Identifier":"0936","Name":"Armarouge","IsShiny":true,"IsAvailable":true,"IsEmpty":false,"Serebii":"armarouge"},{"Identifier":"0937","Name":"Ceruledge","IsShiny":true,"IsAvailable":true,"IsEmpty":false,"Serebii":"ceruledge"},{"Identifier":"0938","Name":"Tadbulb","IsShiny":true,"IsAvailable":true,"IsEmpty":false,"Serebii":"tadbulb"},{"Identifier":"0939","Name":"Bellibolt","IsShiny":true,"IsAvailable":true,"IsEmpty":false,"Serebii":"bellibolt"}]},{"BoxNumber":16,"Slots":[{"Identifier":"0940","Name":"Wattrel","IsShiny":true,"IsAvailable":true,"IsEmpty":false,"Serebii":"wattrel"},{"Identifier":"0941","Name":"Kilowattrel","IsShiny":true,"IsAvailable":true,"IsEmpty":false,"Serebii":"kilowattrel"},{"Identifier":"0942","Name":"Maschiff","IsShiny":true,"IsAvailable":true,"IsEmpty":false,"Serebii":"maschiff"},{"Identifier":"0943","Name":"Mabosstiff","IsShiny":true,"IsAvailable":true,"IsEmpty":false,"Serebii":"mabosstiff"},{"Identifier":"0944","Name":"Shroodle","IsShiny":true,"IsAvailable":true,"IsEmpty":false,"Serebii":"shroodle"},{"Identifier":"0945","Name":"Grafaiai","IsShiny":true,"IsAvailable":true,"IsEmpty":false,"Serebii":"grafaiai"},{"Identifier":"0946","Name":"Bramblin","IsShiny":true,"IsAvailable":true,"IsEmpty":false,"Serebii":"bramblin"},{"Identifier":"0947","Name":"Brambleghast","IsShiny":true,"IsAvailable":true,"IsEmpty":false,"Serebii":"brambleghast"},{"Identifier":"0948","Name":"Toedscool","IsShiny":true,"IsAvailable":true,"IsEmpty":false,"Serebii":"toedscool"},{"Identifier":"0949","Name":"Toedscruel","IsShiny":true,"IsAvailable":true,"IsEmpty":false,"Serebii":"toedscruel"},{"Identifier":"0950","Name":"Klawf","IsShiny":true,"IsAvailable":true,"IsEmpty":false,"Serebii":"klawf"},{"Identifier":"0951","Name":"Capsakid","IsShiny":true,"IsAvailable":true,"IsEmpty":false,"Serebii":"capsakid"},{"Identifier":"0952","Name":"Scovillain","IsShiny":true,"IsAvailable":true,"IsEmpty":false,"Serebii":"scovillain"},{"Identifier":"0953","Name":"Rellor","IsShiny":true,"IsAvailable":true,"IsEmpty":false,"Serebii":"rellor"},{"Identifier":"0954","Name":"Rabsca","IsShiny":true,"IsAvailable":true,"IsEmpty":false,"Serebii":"rabsca"},{"Identifier":"0955","Name":"Flittle","IsShiny":true,"IsAvailable":true,"IsEmpty":false,"Serebii":"flittle"},{"Identifier":"0956","Name":"Espathra","IsShiny":true,"IsAvailable":true,"IsEmpty":false,"Serebii":"espathra"},{"Identifier":"0957","Name":"Tinkatink","IsShiny":true,"IsAvailable":true,"IsEmpty":false,"Serebii":"tinkatink"},{"Identifier":"0958","Name":"Tinkatuff","IsShiny":true,"IsAvailable":true,"IsEmpty":false,"Serebii":"tinkatuff"},{"Identifier":"0959","Name":"Tinkaton","IsShiny":true,"IsAvailable":true,"IsEmpty":false,"Serebii":"tinkaton"},{"Identifier":"0960","Name":"Wiglett","IsShiny":true,"IsAvailable":true,"IsEmpty":false,"Serebii":"wiglett"},{"Identifier":"0961","Name":"Wugtrio","IsShiny":true,"IsAvailable":true,"IsEmpty":false,"Serebii":"wugtrio"},{"Identifier":"0962","Name":"Bombirdier","IsShiny":true,"IsAvailable":true,"IsEmpty":false,"Serebii":"bombirdier"},{"Identifier":"0963","Name":"Finizen","IsShiny":true,"IsAvailable":true,"IsEmpty":false,"Serebii":"finizen"},{"Identifier":"0964","Name":"Palafin","IsShiny":true,"IsAvailable":true,"IsEmpty":false,"Serebii":"palafin"},{"Identifier":"0965","Name":"Varoom","IsShiny":true,"IsAvailable":true,"IsEmpty":false,"Serebii":"varoom"},{"Identifier":"0966","Name":"Revavroom","IsShiny":true,"IsAvailable":true,"IsEmpty":false,"Serebii":"revavroom"},{"Identifier":"0967","Name":"Cyclizar","IsShiny":true,"IsAvailable":true,"IsEmpty":false,"Serebii":"cyclizar"},{"Identifier":"0968","Name":"Orthworm","IsShiny":true,"IsAvailable":true,"IsEmpty":false,"Serebii":"orthworm"},{"Identifier":"0969","Name":"Glimmet","IsShiny":true,"IsAvailable":true,"IsEmpty":false,"Serebii":"glimmet"}]},{"BoxNumber":17,"Slots":[{"Identifier":"0970","Name":"Glimmora","IsShiny":true,"IsAvailable":true,"IsEmpty":false,"Serebii":"glimmora"},{"Identifier":"0971","Name":"Greavard","IsShiny":true,"IsAvailable":true,"IsEmpty":false,"Serebii":"greavard"},{"Identifier":"0972","Name":"Houndstone","IsShiny":true,"IsAvailable":true,"IsEmpty":false,"Serebii":"houndstone"},{"Identifier":"0973","Name":"Flamigo","IsShiny":true,"IsAvailable":true,"IsEmpty":false,"Serebii":"flamigo"},{"Identifier":"0974","Name":"Cetoddle","IsShiny":true,"IsAvailable":true,"IsEmpty":false,"Serebii":"cetoddle"},{"Identifier":"0975","Name":"Cetitan","IsShiny":true,"IsAvailable":true,"IsEmpty":false,"Serebii":"cetitan"},{"Identifier":"0976","Name":"Veluza","IsShiny":true,"IsAvailable":true,"IsEmpty":false,"Serebii":"veluza"},{"Identifier":"0977","Name":"Dondozo","IsShiny":true,"IsAvailable":true,"IsEmpty":false,"Serebii":"dondozo"},{"Identifier":"0978","Name":"Tatsugiri","IsShiny":true,"IsAvailable":true,"IsEmpty":false,"Serebii":"tatsugiri"},{"Identifier":"0978-droopy","Name":"Tatsugiri Droopy Form","IsShiny":true,"IsAvailable":true,"IsEmpty":false,"Serebii":"Tatsugiri"},{"Identifier":"0978-sketchy","Name":"Tatsugiri Sketchy Form","IsShiny":true,"IsAvailable":true,"IsEmpty":false,"Serebii":"Tatsugiri"},{"Identifier":"0979","Name":"Annihilape","IsShiny":true,"IsAvailable":true,"IsEmpty":false,"Serebii":"annihilape"},{"Identifier":"0980","Name":"Clodsire","IsShiny":true,"IsAvailable":true,"IsEmpty":false,"Serebii":"clodsire"},{"Identifier":"0981","Name":"Farigiraf","IsShiny":true,"IsAvailable":true,"IsEmpty":false,"Serebii":"farigiraf"},{"Identifier":"0982","Name":"Dudunsparce","IsShiny":true,"IsAvailable":true,"IsEmpty":false,"Serebii":"dudunsparce"},{"Identifier":"0982-three-segment","Name":"Dudunsparce Three-Segment Form","IsShiny":true,"IsAvailable":true,"IsEmpty":false,"Serebii":"Dudunsparce"},{"Identifier":"0983","Name":"Kingambit","IsShiny":true,"IsAvailable":true,"IsEmpty":false,"Serebii":"kingambit"},{"Identifier":"0984","Name":"Great Tusk","IsShiny":true,"IsAvailable":true,"IsEmpty":false,"Serebii":"greattusk"},{"Identifier":"0985","Name":"Scream Tail","IsShiny":true,"IsAvailable":true,"IsEmpty":false,"Serebii":"screamtail"},{"Identifier":"0986","Name":"Brute Bonnet","IsShiny":true,"IsAvailable":true,"IsEmpty":false,"Serebii":"brutebonnet"},{"Identifier":"0987","Name":"Flutter Mane","IsShiny":true,"IsAvailable":true,"IsEmpty":false,"Serebii":"fluttermane"},{"Identifier":"0988","Name":"Slither Wing","IsShiny":true,"IsAvailable":true,"IsEmpty":false,"Serebii":"slitherwing"},{"Identifier":"0989","Name":"Sandy Shocks","IsShiny":true,"IsAvailable":true,"IsEmpty":false,"Serebii":"sandyshocks"},{"Identifier":"0990","Name":"Iron Treads","IsShiny":true,"IsAvailable":true,"IsEmpty":false,"Serebii":"irontreads"},{"Identifier":"0991","Name":"Iron Bundle","IsShiny":true,"IsAvailable":true,"IsEmpty":false,"Serebii":"ironbundle"},{"Identifier":"0992","Name":"Iron Hands","IsShiny":true,"IsAvailable":true,"IsEmpty":false,"Serebii":"ironhands"},{"Identifier":"0993","Name":"Iron Jugulis","IsShiny":true,"IsAvailable":true,"IsEmpty":false,"Serebii":"ironjugulis"},{"Identifier":"0994","Name":"Iron Moth","IsShiny":true,"IsAvailable":true,"IsEmpty":false,"Serebii":"ironmoth"},{"Identifier":"0995","Name":"Iron Thorns","IsShiny":true,"IsAvailable":true,"IsEmpty":false,"Serebii":"ironthorns"},{"Identifier":"0996","Name":"Frigibax","IsShiny":true,"IsAvailable":true,"IsEmpty":false,"Serebii":"frigibax"}]},{"BoxNumber":18,"Slots":[{"Identifier":"0997","Name":"Arctibax","IsShiny":true,"IsAvailable":true,"IsEmpty":false,"Serebii":"arctibax"},{"Identifier":"0998","Name":"Baxcalibur","IsShiny":true,"IsAvailable":true,"IsEmpty":false,"Serebii":"baxcalibur"},{"Identifier":"0999","Name":"Gimmighoul","IsShiny":true,"IsAvailable":false,"IsEmpty":false,"Serebii":"gimmighoul"},{"Identifier":"0999-roaming","Name":"Gimmighoul Roaming Form","IsShiny":true,"IsAvailable":false,"IsEmpty":false,"Serebii":"Gimmighoul"},{"Identifier":"1000","Name":"Gholdengo","IsShiny":true,"IsAvailable":false,"IsEmpty":false,"Serebii":"gholdengo"},{"Identifier":"1001","Name":"Wo-Chien","IsShiny":true,"IsAvailable":false,"IsEmpty":false,"Serebii":"wochien"},{"Identifier":"1002","Name":"Chien-Pao","IsShiny":true,"IsAvailable":false,"IsEmpty":false,"Serebii":"chienpao"},{"Identifier":"1003","Name":"Ting-Lu","IsShiny":true,"IsAvailable":false,"IsEmpty":false,"Serebii":"tinglu"},{"Identifier":"1004","Name":"Chi-Yu","IsShiny":true,"IsAvailable":false,"IsEmpty":false,"Serebii":"chiyu"},{"Identifier":"1005","Name":"Roaring Moon","IsShiny":true,"IsAvailable":true,"IsEmpty":false,"Serebii":"roaringmoon"},{"Identifier":"1006","Name":"Iron Valiant","IsShiny":true,"IsAvailable":true,"IsEmpty":false,"Serebii":"ironvaliant"},{"Identifier":"1007","Name":"Koraidon","IsShiny":true,"IsAvailable":false,"IsEmpty":false,"Serebii":"koraidon"},{"Identifier":"1008","Name":"Miraidon","IsShiny":true,"IsAvailable":false,"IsEmpty":false,"Serebii":"miraidon"},{"Identifier":"1009","Name":"Walking Wake","IsShiny":true,"IsAvailable":false,"IsEmpty":false,"Serebii":"walkingwake"},{"Identifier":"1010","Name":"Iron Leaves","IsShiny":true,"IsAvailable":false,"IsEmpty":false,"Serebii":"ironleaves"},{"Identifier":null,"Name":null,"IsShiny":false,"IsAvailable":false,"IsEmpty":true,"Serebii":null},{"Identifier":null,"Name":null,"IsShiny":false,"IsAvailable":false,"IsEmpty":true,"Serebii":null},{"Identifier":null,"Name":null,"IsShiny":false,"IsAvailable":false,"IsEmpty":true,"Serebii":null},{"Identifier":null,"Name":null,"IsShiny":false,"IsAvailable":false,"IsEmpty":true,"Serebii":null},{"Identifier":null,"Name":null,"IsShiny":false,"IsAvailable":false,"IsEmpty":true,"Serebii":null},{"Identifier":null,"Name":null,"IsShiny":false,"IsAvailable":false,"IsEmpty":true,"Serebii":null},{"Identifier":null,"Name":null,"IsShiny":false,"IsAvailable":false,"IsEmpty":true,"Serebii":null},{"Identifier":null,"Name":null,"IsShiny":false,"IsAvailable":false,"IsEmpty":true,"Serebii":null},{"Identifier":null,"Name":null,"IsShiny":false,"IsAvailable":false,"IsEmpty":true,"Serebii":null},{"Identifier":null,"Name":null,"IsShiny":false,"IsAvailable":false,"IsEmpty":true,"Serebii":null},{"Identifier":null,"Name":null,"IsShiny":false,"IsAvailable":false,"IsEmpty":true,"Serebii":null},{"Identifier":null,"Name":null,"IsShiny":false,"IsAvailable":false,"IsEmpty":true,"Serebii":null},{"Identifier":null,"Name":null,"IsShiny":false,"IsAvailable":false,"IsEmpty":true,"Serebii":null},{"Identifier":null,"Name":null,"IsShiny":false,"IsAvailable":false,"IsEmpty":true,"Serebii":null},{"Identifier":null,"Name":null,"IsShiny":false,"IsAvailable":false,"IsEmpty":true,"Serebii":null}]},{"BoxNumber":19,"Slots":[{"Identifier":"0052-galar","Name":"Galarian Meowth","IsShiny":true,"IsAvailable":true,"IsEmpty":false,"Serebii":"meowth"},{"Identifier":null,"Name":null,"IsShiny":false,"IsAvailable":false,"IsEmpty":true,"Serebii":null},{"Identifier":null,"Name":null,"IsShiny":false,"IsAvailable":false,"IsEmpty":true,"Serebii":null},{"Identifier":null,"Name":null,"IsShiny":false,"IsAvailable":false,"IsEmpty":true,"Serebii":null},{"Identifier":null,"Name":null,"IsShiny":false,"IsAvailable":false,"IsEmpty":true,"Serebii":null},{"Identifier":null,"Name":null,"IsShiny":false,"IsAvailable":false,"IsEmpty":true,"Serebii":null},{"Identifier":null,"Name":null,"IsShiny":false,"IsAvailable":false,"IsEmpty":true,"Serebii":null},{"Identifier":null,"Name":null,"IsShiny":false,"IsAvailable":false,"IsEmpty":true,"Serebii":null},{"Identifier":null,"Name":null,"IsShiny":false,"IsAvailable":false,"IsEmpty":true,"Serebii":null},{"Identifier":null,"Name":null,"IsShiny":false,"IsAvailable":false,"IsEmpty":true,"Serebii":null},{"Identifier":null,"Name":null,"IsShiny":false,"IsAvailable":false,"IsEmpty":true,"Serebii":null},{"Identifier":null,"Name":null,"IsShiny":false,"IsAvailable":false,"IsEmpty":true,"Serebii":null},{"Identifier":null,"Name":null,"IsShiny":false,"IsAvailable":false,"IsEmpty":true,"Serebii":null},{"Identifier":null,"Name":null,"IsShiny":false,"IsAvailable":false,"IsEmpty":true,"Serebii":null},{"Identifier":null,"Name":null,"IsShiny":false,"IsAvailable":false,"IsEmpty":true,"Serebii":null},{"Identifier":null,"Name":null,"IsShiny":false,"IsAvailable":false,"IsEmpty":true,"Serebii":null},{"Identifier":null,"Name":null,"IsShiny":false,"IsAvailable":false,"IsEmpty":true,"Serebii":null},{"Identifier":null,"Name":null,"IsShiny":false,"IsAvailable":false,"IsEmpty":true,"Serebii":null},{"Identifier":null,"Name":null,"IsShiny":false,"IsAvailable":false,"IsEmpty":true,"Serebii":null},{"Identifier":null,"Name":null,"IsShiny":false,"IsAvailable":false,"IsEmpty":true,"Serebii":null},{"Identifier":null,"Name":null,"IsShiny":false,"IsAvailable":false,"IsEmpty":true,"Serebii":null},{"Identifier":null,"Name":null,"IsShiny":false,"IsAvailable":false,"IsEmpty":true,"Serebii":null},{"Identifier":null,"Name":null,"IsShiny":false,"IsAvailable":false,"IsEmpty":true,"Serebii":null},{"Identifier":null,"Name":null,"IsShiny":false,"IsAvailable":false,"IsEmpty":true,"Serebii":null},{"Identifier":null,"Name":null,"IsShiny":false,"IsAvailable":false,"IsEmpty":true,"Serebii":null},{"Identifier":null,"Name":null,"IsShiny":false,"IsAvailable":false,"IsEmpty":true,"Serebii":null},{"Identifier":null,"Name":null,"IsShiny":false,"IsAvailable":false,"IsEmpty":true,"Serebii":null},{"Identifier":null,"Name":null,"IsShiny":false,"IsAvailable":false,"IsEmpty":true,"Serebii":null},{"Identifier":null,"Name":null,"IsShiny":false,"IsAvailable":false,"IsEmpty":true,"Serebii":null},{"Identifier":null,"Name":null,"IsShiny":false,"IsAvailable":false,"IsEmpty":true,"Serebii":null}]},{"BoxNumber":20,"Slots":[{"Identifier":"0570-hisui","Name":"Hisuian Zorua","IsShiny":true,"IsAvailable":true,"IsEmpty":false,"Serebii":"zorua"},{"Identifier":"0571-hisui","Name":"Hisuian Zoroark","IsShiny":true,"IsAvailable":true,"IsEmpty":false,"Serebii":"zoroark"},{"Identifier":null,"Name":null,"IsShiny":false,"IsAvailable":false,"IsEmpty":true,"Serebii":null},{"Identifier":null,"Name":null,"IsShiny":false,"IsAvailable":false,"IsEmpty":true,"Serebii":null},{"Identifier":null,"Name":null,"IsShiny":false,"IsAvailable":false,"IsEmpty":true,"Serebii":null},{"Identifier":null,"Name":null,"IsShiny":false,"IsAvailable":false,"IsEmpty":true,"Serebii":null},{"Identifier":null,"Name":null,"IsShiny":false,"IsAvailable":false,"IsEmpty":true,"Serebii":null},{"Identifier":null,"Name":null,"IsShiny":false,"IsAvailable":false,"IsEmpty":true,"Serebii":null},{"Identifier":null,"Name":null,"IsShiny":false,"IsAvailable":false,"IsEmpty":true,"Serebii":null},{"Identifier":null,"Name":null,"IsShiny":false,"IsAvailable":false,"IsEmpty":true,"Serebii":null},{"Identifier":null,"Name":null,"IsShiny":false,"IsAvailable":false,"IsEmpty":true,"Serebii":null},{"Identifier":null,"Name":null,"IsShiny":false,"IsAvailable":false,"IsEmpty":true,"Serebii":null},{"Identifier":null,"Name":null,"IsShiny":false,"IsAvailable":false,"IsEmpty":true,"Serebii":null},{"Identifier":null,"Name":null,"IsShiny":false,"IsAvailable":false,"IsEmpty":true,"Serebii":null},{"Identifier":null,"Name":null,"IsShiny":false,"IsAvailable":false,"IsEmpty":true,"Serebii":null},{"Identifier":null,"Name":null,"IsShiny":false,"IsAvailable":false,"IsEmpty":true,"Serebii":null},{"Identifier":null,"Name":null,"IsShiny":false,"IsAvailable":false,"IsEmpty":true,"Serebii":null},{"Identifier":null,"Name":null,"IsShiny":false,"IsAvailable":false,"IsEmpty":true,"Serebii":null},{"Identifier":null,"Name":null,"IsShiny":false,"IsAvailable":false,"IsEmpty":true,"Serebii":null},{"Identifier":null,"Name":null,"IsShiny":false,"IsAvailable":false,"IsEmpty":true,"Serebii":null},{"Identifier":null,"Name":null,"IsShiny":false,"IsAvailable":false,"IsEmpty":true,"Serebii":null},{"Identifier":null,"Name":null,"IsShiny":false,"IsAvailable":false,"IsEmpty":true,"Serebii":null},{"Identifier":null,"Name":null,"IsShiny":false,"IsAvailable":false,"IsEmpty":true,"Serebii":null},{"Identifier":null,"Name":null,"IsShiny":false,"IsAvailable":false,"IsEmpty":true,"Serebii":null},{"Identifier":null,"Name":null,"IsShiny":false,"IsAvailable":false,"IsEmpty":true,"Serebii":null},{"Identifier":null,"Name":null,"IsShiny":false,"IsAvailable":false,"IsEmpty":true,"Serebii":null},{"Identifier":null,"Name":null,"IsShiny":false,"IsAvailable":false,"IsEmpty":true,"Serebii":null},{"Identifier":null,"Name":null,"IsShiny":false,"IsAvailable":false,"IsEmpty":true,"Serebii":null},{"Identifier":null,"Name":null,"IsShiny":false,"IsAvailable":false,"IsEmpty":true,"Serebii":null},{"Identifier":null,"Name":null,"IsShiny":false,"IsAvailable":false,"IsEmpty":true,"Serebii":null}]},{"BoxNumber":21,"Slots":[{"Identifier":"0128-paldea","Name":"Paldean Tauros","IsShiny":true,"IsAvailable":true,"IsEmpty":false,"Serebii":"Tauros"},{"Identifier":"0128-paldea-fire","Name":"Paldean Tauros - Blaze Breed","IsShiny":true,"IsAvailable":true,"IsEmpty":false,"Serebii":"Tauros"},{"Identifier":"0128-paldea-water","Name":"Paldean Tauros - Aqua Breed","IsShiny":true,"IsAvailable":true,"IsEmpty":false,"Serebii":"Tauros"},{"Identifier":"0194-paldea","Name":"Paldean Wooper","IsShiny":true,"IsAvailable":true,"IsEmpty":false,"Serebii":"Wooper"},{"Identifier":null,"Name":null,"IsShiny":false,"IsAvailable":false,"IsEmpty":true,"Serebii":null},{"Identifier":null,"Name":null,"IsShiny":false,"IsAvailable":false,"IsEmpty":true,"Serebii":null},{"Identifier":null,"Name":null,"IsShiny":false,"IsAvailable":false,"IsEmpty":true,"Serebii":null},{"Identifier":null,"Name":null,"IsShiny":false,"IsAvailable":false,"IsEmpty":true,"Serebii":null},{"Identifier":null,"Name":null,"IsShiny":false,"IsAvailable":false,"IsEmpty":true,"Serebii":null},{"Identifier":null,"Name":null,"IsShiny":false,"IsAvailable":false,"IsEmpty":true,"Serebii":null},{"Identifier":null,"Name":null,"IsShiny":false,"IsAvailable":false,"IsEmpty":true,"Serebii":null},{"Identifier":null,"Name":null,"IsShiny":false,"IsAvailable":false,"IsEmpty":true,"Serebii":null},{"Identifier":null,"Name":null,"IsShiny":false,"IsAvailable":false,"IsEmpty":true,"Serebii":null},{"Identifier":null,"Name":null,"IsShiny":false,"IsAvailable":false,"IsEmpty":true,"Serebii":null},{"Identifier":null,"Name":null,"IsShiny":false,"IsAvailable":false,"IsEmpty":true,"Serebii":null},{"Identifier":null,"Name":null,"IsShiny":false,"IsAvailable":false,"IsEmpty":true,"Serebii":null},{"Identifier":null,"Name":null,"IsShiny":false,"IsAvailable":false,"IsEmpty":true,"Serebii":null},{"Identifier":null,"Name":null,"IsShiny":false,"IsAvailable":false,"IsEmpty":true,"Serebii":null},{"Identifier":null,"Name":null,"IsShiny":false,"IsAvailable":false,"IsEmpty":true,"Serebii":null},{"Identifier":null,"Name":null,"IsShiny":false,"IsAvailable":false,"IsEmpty":true,"Serebii":null},{"Identifier":null,"Name":null,"IsShiny":false,"IsAvailable":false,"IsEmpty":true,"Serebii":null},{"Identifier":null,"Name":null,"IsShiny":false,"IsAvailable":false,"IsEmpty":true,"Serebii":null},{"Identifier":null,"Name":null,"IsShiny":false,"IsAvailable":false,"IsEmpty":true,"Serebii":null},{"Identifier":null,"Name":null,"IsShiny":false,"IsAvailable":false,"IsEmpty":true,"Serebii":null},{"Identifier":null,"Name":null,"IsShiny":false,"IsAvailable":false,"IsEmpty":true,"Serebii":null},{"Identifier":null,"Name":null,"IsShiny":false,"IsAvailable":false,"IsEmpty":true,"Serebii":null},{"Identifier":null,"Name":null,"IsShiny":false,"IsAvailable":false,"IsEmpty":true,"Serebii":null},{"Identifier":null,"Name":null,"IsShiny":false,"IsAvailable":false,"IsEmpty":true,"Serebii":null},{"Identifier":null,"Name":null,"IsShiny":false,"IsAvailable":false,"IsEmpty":true,"Serebii":null},{"Identifier":null,"Name":null,"IsShiny":false,"IsAvailable":false,"IsEmpty":true,"Serebii":null}]}]}